math_base/__init__.py
math_base/cli.py
math_base/dice.py
math_base/math_base.py
math_base-0.1.3.dist-info/AUTHORS.rst
math_base-0.1.3.dist-info/LICENSE
math_base-0.1.3.dist-info/METADATA
math_base-0.1.3.dist-info/WHEEL
math_base-0.1.3.dist-info/entry_points.txt
math_base-0.1.3.dist-info/top_level.txt
math_base-0.1.3.dist-info/RECORD
