Metadata-Version: 2.1
Name: math-base
Version: 0.1.3
Summary: math base package
Home-page: https://github.com/hatter30/math_base
Author: Oh June
Author-email: tic.for.tac@gmail.com
License: MIT license
Keywords: math_base
Platform: UNKNOWN
Classifier: Development Status :: 2 - Pre-Alpha
Classifier: Intended Audience :: Developers
Classifier: License :: OSI Approved :: MIT License
Classifier: Natural Language :: English
Classifier: Programming Language :: Python :: 3
Classifier: Programming Language :: Python :: 3.5
Classifier: Programming Language :: Python :: 3.6
Classifier: Programming Language :: Python :: 3.7
Classifier: Programming Language :: Python :: 3.8
Requires-Python: >=3.5
Requires-Dist: Click (>=7.0)
